snips_app_helpers/__init__.py
snips_app_helpers/__main__.py
snips_app_helpers/cli.py
snips_app_helpers/utils.py
snips_app_helpers/snips/__init__.py
snips_app_helpers/snips/assistant.py
snips_app_helpers/snips/dataset/__init__.py
snips_app_helpers/snips/dataset/constants.py
snips_app_helpers/snips/dataset/entity.py
snips_app_helpers/snips/dataset/exceptions.py
snips_app_helpers/snips/dataset/intent.py
snips_app_helpers/specs/__init__.py
snips_app_helpers/specs/action.py
snips_app_helpers/specs/assistant.py
snips_app_helpers/specs/message.py
snips_app_helpers-0.0.11.dist-info/DESCRIPTION.rst
snips_app_helpers-0.0.11.dist-info/METADATA
snips_app_helpers-0.0.11.dist-info/RECORD
snips_app_helpers-0.0.11.dist-info/WHEEL
snips_app_helpers-0.0.11.dist-info/entry_points.txt
snips_app_helpers-0.0.11.dist-info/metadata.json
snips_app_helpers-0.0.11.dist-info/top_level.txt
