Metadata-Version: 2.0
Name: snips-app-helpers
Version: 0.0.11
Summary: Handful of cli and other tools to develop with confidence Snips services
Home-page: https://github.com/dreamermind/snips-app-helpers
Author: Dreamermind
Author-email: sigmer66@gmail.com
License: MIT license
Project-URL: Issue Tracker, https://github.com/dreamermind/snips-app-helpers/issues
Project-URL: Documentation, https://snips-app-helpers.readthedocs.io/
Project-URL: Changelog, https://snips-app-helpers.readthedocs.io/en/latest/changelog.html
Platform: UNKNOWN
Classifier: Development Status :: 5 - Production/Stable
Classifier: Intended Audience :: Developers
Classifier: License :: OSI Approved :: MIT License
Classifier: Operating System :: Unix
Classifier: Operating System :: POSIX
Classifier: Programming Language :: Python
Classifier: Programming Language :: Python :: 3
Classifier: Programming Language :: Python :: 3.5
Classifier: Programming Language :: Python :: 3.6
Classifier: Programming Language :: Python :: 3.7
Classifier: Programming Language :: Python :: Implementation :: CPython
Classifier: Programming Language :: Python :: Implementation :: PyPy
Classifier: Topic :: Utilities
Requires-Python: !=3.0.*, !=3.1.*, !=3.2.*, !=3.3.*, !=3.4.*
Requires-Dist: click
Requires-Dist: colorama
Requires-Dist: pyyaml
